phone_number_validator/__init__.py
phone_number_validator/validator.py
rowans_phone_number_validator-0.1.0.dist-info/METADATA
rowans_phone_number_validator-0.1.0.dist-info/WHEEL
rowans_phone_number_validator-0.1.0.dist-info/RECORD
