Metadata-Version: 2.1
Name: rowans-phone-number-validator
Version: 0.1.0
Summary: 
Author: Rowan Murray
Author-email: 67557980+RowMur@users.noreply.github.com
Requires-Python: >=3.11,<4.0
Classifier: Programming Language :: Python :: 3
Classifier: Programming Language :: Python :: 3.11
Requires-Dist: requests (>=2.31.0,<3.0.0)
